bayex/__init__.py
bayex/acq.py
bayex/domain.py
bayex/gp.py
bayex/gp_test.py
bayex/optimizer.py
bayex/optimizer_test.py
bayex-0.2.2.dist-info/LICENSE
bayex-0.2.2.dist-info/METADATA
bayex-0.2.2.dist-info/WHEEL
bayex-0.2.2.dist-info/top_level.txt
bayex-0.2.2.dist-info/RECORD
