Metadata-Version: 2.2
Name: bayex
Version: 0.2.2
Summary: Minimal Bayesian Optimization Implementation with Gaussian Processes written in JAX.
Author-email: Albert Alonso <alonfnt@pm.me>
License: MIT License
Project-URL: Homepage, https://github.com/alonfnt/bayex
Project-URL: Documentation, https://github.com/alonfnt/bayex
Project-URL: Source, https://github.com/alonfnt/bayex
Project-URL: Bug Tracker, https://github.com/alonfnt/bayex/issues
Keywords: jax,bayesian-optimization,automatic-differentiation,gaussian-process,machine-learning
Classifier: Development Status :: 3 - Alpha
Classifier: Intended Audience :: Developers
Classifier: Intended Audience :: Science/Research
Classifier: Topic :: Scientific/Engineering
Classifier: License :: OSI Approved :: MIT License
Classifier: Programming Language :: Python :: 3
Classifier: Programming Language :: Python :: 3.9
Classifier: Programming Language :: Python :: 3.10
Classifier: Programming Language :: Python :: 3.11
Requires-Python: >=3.9
License-File: LICENSE
Requires-Dist: jax
Requires-Dist: jaxlib
Requires-Dist: numpy
Provides-Extra: dev
Requires-Dist: pytest; extra == "dev"
